wepoll/__init__.pxd
wepoll/__init__.py
wepoll/_wepoll.c
wepoll/_wepoll.cp311-win_arm64.pyd
wepoll/_wepoll.pxd
wepoll/_wepoll.pyi
wepoll/_wepoll.pyx
wepoll/flags.py
wepoll/loop.py
wepoll/msvc_compat.h
wepoll/selector.py
wepoll/socket.pxd
wepoll-0.1.5.dist-info/METADATA
wepoll-0.1.5.dist-info/WHEEL
wepoll-0.1.5.dist-info/top_level.txt
wepoll-0.1.5.dist-info/RECORD
