Metadata-Version: 2.4
Name: wepoll
Version: 0.1.5
Summary: Cython adaptation of the wepoll C Library providing epoll selectors to windows
Author-email: Vizonex <VizonexBusiness@gmail.com>
License: MIT License
Project-URL: homepage, https://github.com/Vizonex/pywepoll
Project-URL: repository, https://github.com/Vizonex/pywepoll.git
Requires-Python: >=3.10
